modlinear/__init__.py
modlinear/tool.py
modlinear/utils.py
modlinear-1.0.2.dist-info/METADATA
modlinear-1.0.2.dist-info/WHEEL
modlinear-1.0.2.dist-info/licenses/LICENSE
modlinear-1.0.2.dist-info/RECORD
