Metadata-Version: 2.3
Name: modlinear
Version: 1.0.2
Summary: A wrapped package to linearize the nonlinear continuous/discrete model. Including **numerical** and **symbolic** calculations.
Project-URL: Homepage, https://github.com/QiYuan-Zhang/ModLinear
Project-URL: Issues, https://github.com/QiYuan-Zhang/ModLinear/issues
Project-URL: Introduction, https://qiyuan-zhang.github.io/my-toolbox/2024/04/25/Developed-modlinear.html
Author-email: Xuewen Zhang <xuewen.zhang741@outlook.com>
Maintainer-email: Xuewen Zhang <xuewen.zhang741@outlook.com>
License:                                 Apache License
License-File: LICENSE
Keywords: Linear model,Modeling,continuous model,continuous to discrete model,discrete model,model linearization,nonlinear model
Classifier: Development Status :: 4 - Beta
Classifier: Intended Audience :: Developers
Classifier: License :: OSI Approved :: Apache Software License
Classifier: Programming Language :: Python :: 3
Classifier: Programming Language :: Python :: 3.6
Classifier: Programming Language :: Python :: 3.7
Classifier: Programming Language :: Python :: 3.8
Classifier: Programming Language :: Python :: 3.9
Classifier: Topic :: Software Development :: Build Tools
Requires-Python: >=3.6
Requires-Dist: casadi
Requires-Dist: control
Requires-Dist: matplotlib
Requires-Dist: numpy
